jua/__init__.py
jua/_api.py
jua/client.py
jua/logging.py
jua/py.typed
jua/_utils/__init__.py
jua/_utils/dataset.py
jua/_utils/optional_progress_bar.py
jua/_utils/remove_none_from_dict.py
jua/_utils/spinner.py
jua/errors/__init__.py
jua/errors/api_errors.py
jua/errors/jua_error.py
jua/errors/model_errors.py
jua/market_aggregates/__init__.py
jua/market_aggregates/energy_market.py
jua/market_aggregates/market_aggregates.py
jua/market_aggregates/model_run.py
jua/market_aggregates/variables.py
jua/scripts/__init__.py
jua/scripts/auth.py
jua/scripts/jua.py
jua/settings/__init__.py
jua/settings/authentication.py
jua/settings/jua_settings.py
jua/types/__init__.py
jua/types/countries.py
jua/types/geo.py
jua/types/market_zones.py
jua/weather/__init__.py
jua/weather/_api.py
jua/weather/_jua_dataset.py
jua/weather/_model.py
jua/weather/_model_meta.py
jua/weather/_query_engine.py
jua/weather/_stream.py
jua/weather/_weather.py
jua/weather/_xarray_patches.py
jua/weather/conversions.py
jua/weather/forecast.py
jua/weather/hindcast.py
jua/weather/models.py
jua/weather/statistics.py
jua/weather/variables.py
jua/weather/_lazy_loading/__init__.py
jua/weather/_lazy_loading/backend.py
jua/weather/_lazy_loading/cache.py
jua/weather/_types/__init__.py
jua/weather/_types/api_payload_types.py
jua/weather/_types/api_response_types.py
jua/weather/_types/forecast.py
jua/weather/_types/pagination.py
jua/weather/_types/query_payload_types.py
jua/weather/_types/query_response_types.py
jua/weather/_types/raw_file_access.py
jua-0.19.3.dist-info/METADATA
jua-0.19.3.dist-info/WHEEL
jua-0.19.3.dist-info/entry_points.txt
jua-0.19.3.dist-info/licenses/LICENSE
jua-0.19.3.dist-info/RECORD
