Metadata-Version: 2.4
Name: jua
Version: 0.19.3
Summary: Easy access to Jua's weather & power services
Project-URL: Documentation, https://docs.jua.ai
Project-URL: Source, https://github.com/juaAI/jua-python-sdk
Author-email: "Jua.ai AG" <contact@jua.ai>
License-Expression: MIT
License-File: LICENSE
Keywords: energy,energy trading,forecast,hindcast,power,trading,weather,weather forecast
Classifier: Development Status :: 4 - Beta
Classifier: Intended Audience :: Developers
Classifier: License :: OSI Approved :: MIT License
Classifier: Programming Language :: Python :: 3
Classifier: Programming Language :: Python :: 3.11
Classifier: Programming Language :: Python :: 3.12
Classifier: Programming Language :: Python :: 3.13
Requires-Python: >=3.11
Requires-Dist: aiohttp>=3.11.18
Requires-Dist: dask>=2025.4.1
Requires-Dist: fsspec>=2025.3.2
Requires-Dist: numcodecs!=0.16.0
Requires-Dist: pandas>=2.2.3
Requires-Dist: pyarrow>=21.0.0
Requires-Dist: pydantic-settings>=2.8.1
Requires-Dist: pydantic>=2.10.6
Requires-Dist: requests>=2.32.3
Requires-Dist: rich>=14.1.0
Requires-Dist: types-requests>=2.32.0.20250328
Requires-Dist: xarray>=2025.7.0
Requires-Dist: zarr>=3.1.0
Provides-Extra: docs
Requires-Dist: myst-parser>=4.0.1; extra == 'docs'
Requires-Dist: sphinx-autoapi>=3.6.0; extra == 'docs'
Requires-Dist: sphinx-book-theme>=1.1.4; extra == 'docs'
Requires-Dist: sphinx-markdown-builder>=0.6.8; extra == 'docs'
Requires-Dist: sphinx>=8.2.3; extra == 'docs'
Provides-Extra: examples
Requires-Dist: ipykernel>=6.29.5; extra == 'examples'
Provides-Extra: plotting
Requires-Dist: matplotlib>=3.8.0; extra == 'plotting'
